aind_nwb_utils/__init__.py
aind_nwb_utils/nwb_io.py
aind_nwb_utils/utils.py
aind_nwb_utils-0.1.6.dist-info/licenses/LICENSE
aind_nwb_utils-0.1.6.dist-info/METADATA
aind_nwb_utils-0.1.6.dist-info/WHEEL
aind_nwb_utils-0.1.6.dist-info/top_level.txt
aind_nwb_utils-0.1.6.dist-info/RECORD
